{
    "en": {
        "package-container.create": "Create",
        "package-container.index": "№",
        "package-container.name": "Name",
        "package-container.roles": "Roles",
        "package-container.edit": "Edit",
        "package-container.delete": "Delete",
        "package-container.view": "View",
        "package-container.edit_title": "Edit package",
        "package-container.create_title": "Create package",
        "package-container.error": "Error",
        "package-container.unique_name_error": "Unique name validation failed",
        "package-container.roles_businesses_restriction": "Cannot delete package because of roles or businesses"
    },
    "ru": {
        "package-container.create": "Создать",
        "package-container.index": "№",
        "package-container.name": "Название",
        "package-container.roles": "Роли",
        "package-container.edit": "Редактировать",
        "package-container.delete": "Удалить",
        "package-container.view": "Посмотреть",
        "package-container.edit_title": "Редактировать пакет",
        "package-container.create_title": "Создать пакет",
        "package-container.error": "Ошибка",
        "package-container.unique_name_error": "Имя пакета должно быть уникальным",
        "package-container.roles_businesses_restriction": "Нельзя удалить пакет из-за ролей или бизнесов"
    },
    "uk": {
        "package-container.create": "Створити",
        "package-container.index": "№",
        "package-container.name": "Назва",
        "package-container.roles": "Ролі",
        "package-container.edit": "Редагувати",
        "package-container.delete": "Видалити",
        "package-container.view": "Переглянути",
        "package-container.edit_title": "Редагувати пакет",
        "package-container.create_title": "Створити пакет",
        "package-container.error": "Помилка",
        "package-container.unique_name_error": "Ім'я пакета має бути унікальним",
        "package-container.roles_businesses_restriction": "Не можна видалити пакет через наявні ролі та бізнеси"
    }
}
